csa_common_lib/__init__.py
csa_common_lib/classes/__init__.py
csa_common_lib/classes/prediction_options.py
csa_common_lib/classes/prediction_receipt.py
csa_common_lib/classes/prediction_results.py
csa_common_lib/enum_types/__init__.py
csa_common_lib/enum_types/exit_flags.py
csa_common_lib/enum_types/functions.py
csa_common_lib/enum_types/job_types.py
csa_common_lib/enum_types/results.py
csa_common_lib/helpers/__init__.py
csa_common_lib/helpers/_arrays.py
csa_common_lib/helpers/_conversions.py
csa_common_lib/helpers/_os.py
csa_common_lib/helpers/_vault.py
csa_common_lib/toolbox/__init__.py
csa_common_lib/toolbox/_notifier.py
csa_common_lib/toolbox/_validate.py
csa_common_lib/toolbox/classes/__init__.py
csa_common_lib/toolbox/classes/utilities.py
csa_common_lib/toolbox/concurrency/__init__.py
csa_common_lib/toolbox/concurrency/parallel_executor.py
csa_common_lib/toolbox/concurrency/parallel_helpers.py
csa_common_lib/toolbox/database/__init__.py
csa_common_lib/toolbox/database/information.py
csa_common_lib/toolbox/npz/__init__.py
csa_common_lib/toolbox/npz/io_operations.py
csa_common_lib/toolbox/stats/__init__.py
csa_common_lib/toolbox/stats/insights.py
csa_common_lib/toolbox/stats/summary.py
csa_prediction_engine/__init__.py
csa_prediction_engine/api_client.py
csa_prediction_engine/version.py
csa_prediction_engine/bin/__init__.py
csa_prediction_engine/bin/_workers.py
csa_prediction_engine/bin/single_tasks.py
csa_prediction_engine/helpers/__init__.py
csa_prediction_engine/helpers/_auth_manager.py
csa_prediction_engine/helpers/_details_handler.py
csa_prediction_engine/helpers/_payload_handler.py
csa_prediction_engine/helpers/_postmaster.py
csa_prediction_engine/helpers/_router.py
csa_prediction_engine/parallel/__init__.py
csa_prediction_engine/parallel/_dispatchers.py
csa_prediction_engine/parallel/_threaded_predictions.py
csa_prediction_engine/parallel/_workers.py
csa_prediction_engine_alpha-2.0.0.dist-info/METADATA
csa_prediction_engine_alpha-2.0.0.dist-info/WHEEL
csa_prediction_engine_alpha-2.0.0.dist-info/top_level.txt
csa_prediction_engine_alpha-2.0.0.dist-info/RECORD
